astarmiko/__init__.py
astarmiko/async_exec.py
astarmiko/base.py
astarmiko/log_config.py
astarmiko/optional_loggers.py
astarmiko/scripts/__init__.py
astarmiko/scripts/acm.py
astarmiko/scripts/fh.py
astarmiko-0.1.0.dist-info/licenses/LICENSE
astarmiko-0.1.0.dist-info/METADATA
astarmiko-0.1.0.dist-info/WHEEL
astarmiko-0.1.0.dist-info/entry_points.txt
astarmiko-0.1.0.dist-info/top_level.txt
astarmiko-0.1.0.dist-info/RECORD
