Metadata-Version: 2.4
Name: astarmiko
Version: 0.1.0
Summary: Async SSH automation for enterprise network equipment
Home-page: https://github.com/astaraiki/astarmiko
Author: astaraiki
Author-email: Andrey Starkov <astar@andreystarkov.com>
License: MIT
Project-URL: Homepage, https://github.com/astaraiki/astarmiko
Requires-Python: >=3.8
License-File: LICENSE
Requires-Dist: netmiko
Requires-Dist: aiofiles
Requires-Dist: asyncssh
Requires-Dist: tqdm
Requires-Dist: textfsm
Requires-Dist: pyyaml
Requires-Dist: requests
Requires-Dist: pysnmp
Requires-Dist: astarconf
Dynamic: author
Dynamic: home-page
Dynamic: license-file
Dynamic: requires-python
